rrq/runner.py
rrq/registry.py
rrq/job.py
rrq/protocol.py
rrq/client.py
rrq/__init__.py
rrq/telemetry.py
rrq/runner_settings.py
rrq/runner_runtime.py
rrq/cli.py
rrq/exc.py
rrq/producer_ffi.py
rrq/bin/rrq
rrq/bin/librrq_producer.dylib
rrq/bin/README.md
rrq/integrations/__init__.py
rrq/integrations/otel.py
rrq-0.9.9.dist-info/RECORD
rrq-0.9.9.dist-info/WHEEL
rrq-0.9.9.dist-info/entry_points.txt
rrq-0.9.9.dist-info/METADATA
rrq-0.9.9.dist-info/licenses/LICENSE
