Metadata-Version: 2.3
Name: rrq
Version: 0.9.9
Summary: RRQ is a library for creating reliable job queues using Rust, Redis. with language-agnostic producers and workers.
Project-URL: Homepage, https://github.com/getresq/rrq
Project-URL: Bug Tracker, https://github.com/getresq/rrq/issues
Author-email: Mazdak Rezvani <mazdak@me.com>
License-File: LICENSE
Classifier: Intended Audience :: Developers
Classifier: Programming Language :: Python :: 3
Classifier: Programming Language :: Python :: 3.11
Classifier: Programming Language :: Python :: 3.12
Classifier: Programming Language :: Python :: 3.13
Classifier: Programming Language :: Python :: 3.14
Classifier: Topic :: Software Development :: Libraries :: Python Modules
Classifier: Topic :: System :: Distributed Computing
Classifier: Topic :: System :: Monitoring
Requires-Python: >=3.11
Requires-Dist: pydantic>=2.11.4
Requires-Dist: redis[hiredis]>=4.2.0
Provides-Extra: dev
Requires-Dist: pytest-asyncio>=1.0.0; extra == 'dev'
Requires-Dist: pytest-cov>=6.0.0; extra == 'dev'
Requires-Dist: pytest>=8.3.5; extra == 'dev'
Requires-Dist: python-dotenv>=1.2.1; extra == 'dev'
Requires-Dist: ruff==0.14.9; extra == 'dev'
Requires-Dist: ty==0.0.1-alpha.26; extra == 'dev'
